jubin_odd_even-0.1.0.dist-info/licenses/LICENCE
oddoreven/__init__.py
oddoreven/check.py
jubin_odd_even-0.1.0.dist-info/METADATA
jubin_odd_even-0.1.0.dist-info/WHEEL
jubin_odd_even-0.1.0.dist-info/top_level.txt
jubin_odd_even-0.1.0.dist-info/RECORD
