Metadata-Version: 2.4
Name: jubin-odd-even
Version: 0.1.0
Summary: Simple odd or even checking functions
Author: Jubin Joy
Project-URL: Homepage, https://github.com/yourusername/oddoreven
Requires-Python: >=3.7
License-File: LICENCE
Dynamic: license-file
